DEVELOPMENT
LICENSE
MANIFEST.in
README.rst
TODO
app.yaml
appengine.py
babel.cfg
celeryconfig.py
distribute_setup.py
manage.py
pdfserver.cgi
requirements.txt
setup.py
test_settings.py
test_settings_celery.py
pdfserver/__init__.py
pdfserver/database.py
pdfserver/faketask.py
pdfserver/gaemodels.py
pdfserver/gaetask.py
pdfserver/helpers.py
pdfserver/models.py
pdfserver/settings.py
pdfserver/tasks.py
pdfserver/tests.py
pdfserver/util.py
pdfserver/views.py
pdfserver.egg-info/PKG-INFO
pdfserver.egg-info/SOURCES.txt
pdfserver.egg-info/dependency_links.txt
pdfserver.egg-info/requires.txt
pdfserver.egg-info/top_level.txt
pdfserver/static/ajax-loader-circle-white.gif
pdfserver/static/ajax-loader-circle.gif
pdfserver/static/ajax-loader.gif
pdfserver/static/css/jquery-ui.css
pdfserver/static/css/jquery.jnotify.min.css
pdfserver/static/css/pdfserver.css
pdfserver/static/css/images/ui-bg_flat_0_aaaaaa_40x100.png
pdfserver/static/css/images/ui-bg_flat_75_ffffff_40x100.png
pdfserver/static/css/images/ui-bg_glass_55_fbf9ee_1x400.png
pdfserver/static/css/images/ui-bg_glass_65_ffffff_1x400.png
pdfserver/static/css/images/ui-bg_glass_75_dadada_1x400.png
pdfserver/static/css/images/ui-bg_glass_75_e6e6e6_1x400.png
pdfserver/static/css/images/ui-bg_glass_95_fef1ec_1x400.png
pdfserver/static/css/images/ui-bg_highlight-soft_75_cccccc_1x100.png
pdfserver/static/css/images/ui-icons_222222_256x240.png
pdfserver/static/css/images/ui-icons_2e83ff_256x240.png
pdfserver/static/css/images/ui-icons_454545_256x240.png
pdfserver/static/css/images/ui-icons_888888_256x240.png
pdfserver/static/css/images/ui-icons_cd0a0a_256x240.png
pdfserver/static/js/jquery-ui.js
pdfserver/static/js/jquery.jnotify.min.js
pdfserver/static/js/jquery.js
pdfserver/static/js/jquery.validate.min.js
pdfserver/templates/base.html
pdfserver/templates/confirm_delete.html
pdfserver/templates/confirm_delete_all.html
pdfserver/templates/download.html
pdfserver/templates/main.html
pdfserver/templates/uploads.html
pdfserver/translations/de/LC_MESSAGES/messages.mo
pdfserver/translations/de/LC_MESSAGES/messages.po