Metadata-Version: 1.0
Name: pdfserver
Version: 0.6
Summary: Pdfserver is a webservice that offers common PDF operations like joining documents, selecting pages or "n pages on one".
Home-page: http://pdfserverapp.appspot.com/
Author: Christoph Burgmer
Author-email: cburgmer@ira.uka.de
License: BSD License
Platform: UNKNOWN
Classifier: Development Status :: 4 - Beta
Classifier: Intended Audience :: Developers
Classifier: License :: OSI Approved :: BSD License
Classifier: Programming Language :: Python :: 2.5
Classifier: Programming Language :: Python :: 2.6
Classifier: Programming Language :: Python :: 2.7
Classifier: Operating System :: OS Independent
Classifier: Topic :: Office/Business
Classifier: Topic :: Utilities
Classifier: Topic :: Internet :: WWW/HTTP :: WSGI :: Application
